upy_flasher/__init__.py
upy_flasher/flash.py
upy_flasher-0.42.dist-info/DESCRIPTION.rst
upy_flasher-0.42.dist-info/METADATA
upy_flasher-0.42.dist-info/RECORD
upy_flasher-0.42.dist-info/WHEEL
upy_flasher-0.42.dist-info/metadata.json
upy_flasher-0.42.dist-info/top_level.txt
