Metadata-Version: 2.0
Name: upy-flasher
Version: 0.42
Summary: micropython flash script
Home-page: https://github.com/smthnspcl/upy_flasher
Author: Pascal Eberlein
Author-email: pascal@eberlein.io
License: UNKNOWN
Keywords: micropython flasher
Platform: UNKNOWN
Classifier: Development Status :: 3 - Alpha
Classifier: Intended Audience :: Developers
Classifier: Topic :: Software Development :: Build Tools
Classifier: License :: OSI Approved :: MIT License
Classifier: Programming Language :: Python :: 3.6
